pysaurio/__init__.py
pysaurio-0.2.6.dist-info/METADATA
pysaurio-0.2.6.dist-info/RECORD
pysaurio-0.2.6.dist-info/WHEEL
pysaurio-0.2.6.dist-info/top_level.txt
