Metadata-Version: 2.1
Name: pysaurio
Version: 0.2.6
Summary: A tool for searching & extracting information from multiple text files.
Home-page: https://pypi.python.org/pypi/pysaurio
Author: Antonio Suárez Jiménez
Author-email: pherkad13@gmail.com
License: GNU GPLv3
Keywords: pysaurio search extract text csv collect data merge join pyraptor
Platform: UNKNOWN
Classifier: Development Status :: 4 - Beta
Classifier: Intended Audience :: Developers
Classifier: Intended Audience :: System Administrators
Classifier: Topic :: Utilities
Classifier: License :: OSI Approved :: GNU General Public License v3 (GPLv3)
Classifier: Programming Language :: Python :: 3
